randalgo1/__init__.py
randalgo1/app.py
randalgo1-0.1.8.dist-info/entry_points.txt
randalgo1-0.1.8.dist-info/WHEEL
randalgo1-0.1.8.dist-info/METADATA
randalgo1-0.1.8.dist-info/RECORD
