Metadata-Version: 2.1
Name: randalgo1
Version: 0.1.8
Summary: a console app that fetches random question from public api
Author: charles
Author-email: charlesclinton2003@gmail.com
Requires-Python: >=3.0,<4.0
Classifier: Programming Language :: Python :: 3
Classifier: Programming Language :: Python :: 3.4
Classifier: Programming Language :: Python :: 3.5
Classifier: Programming Language :: Python :: 3.6
Classifier: Programming Language :: Python :: 3.7
Classifier: Programming Language :: Python :: 3.8
